chatserver/__init__.py
chatserver/ansi.py
chatserver/chatserver.py
chatserver/clients.py
chatserver/database.py
chatserver-0.1.5.dist-info/entry_points.txt
chatserver-0.1.5.dist-info/LICENSE
chatserver-0.1.5.dist-info/WHEEL
chatserver-0.1.5.dist-info/METADATA
chatserver-0.1.5.dist-info/RECORD
