Metadata-Version: 2.1
Name: chatserver
Version: 0.1.5
Summary: A chatserver written in python
Home-page: https://gitlab.com/mokytis/python-chatserver
License: MIT
Author: Luke Spademan
Author-email: info@lukespademan.com
Requires-Python: >=3.8.0,<4.0.0
Classifier: License :: OSI Approved :: MIT License
Classifier: Programming Language :: Python :: 3
Classifier: Programming Language :: Python :: 3.8
Requires-Dist: sqlalchemy (>=1.3.13,<2.0.0)
Requires-Dist: werkzeug (>=1.0.0,<2.0.0)
Project-URL: Repository, https://gitlab.com/mokytis/python-chatserver
